xlql/__init__.py
xlql/cli.py
xlql/commands/__init__.py
xlql/commands/basic_sql.py
xlql/commands/create_db.py
xlql/commands/delete_db.py
xlql/commands/delete_table.py
xlql/commands/insert.py
xlql/commands/list_db.py
xlql/commands/list_table.py
xlql/commands/query_handler.py
xlql/core/__init__.py
xlql/core/logger_config.py
xlql/core/utils.py
xlql-0.3.5.dist-info/METADATA
xlql-0.3.5.dist-info/WHEEL
xlql-0.3.5.dist-info/entry_points.txt
xlql-0.3.5.dist-info/top_level.txt
xlql-0.3.5.dist-info/RECORD
