Metadata-Version: 2.4
Name: xlql
Version: 0.3.5
Requires-Dist: duckdb>=1.3.2
Requires-Dist: questionary>=2.1.0
Requires-Dist: tabulate>=0.9.0
Requires-Dist: pandas>=2.3.1
Dynamic: description
Dynamic: description-content-type
Dynamic: requires-dist
